saas_ips/__init__.py
saas_ips/__main__.py
saas_ips/base.py
saas_ips/collector.py
saas_ips/logger.py
saas_ips/models.py
saas_ips/services/__init__.py
saas_ips/services/atlassian.py
saas_ips/services/azure.py
saas_ips/services/base.py
saas_ips/services/box.py
saas_ips/services/fastly.py
saas_ips/services/google.py
saas_ips/services/o365.py
saas_ips-0.1.0.dist-info/METADATA
saas_ips-0.1.0.dist-info/WHEEL
saas_ips-0.1.0.dist-info/entry_points.txt
saas_ips-0.1.0.dist-info/RECORD
