Metadata-Version: 2.3
Name: saas-ips
Version: 0.1.0
Summary: A simple python utility to help identify saas service ips
Author: MSAdministrator
Author-email: 10687261+MSAdministrator@users.noreply.github.com
Requires-Python: >=3.13
Classifier: Programming Language :: Python :: 3
Classifier: Programming Language :: Python :: 3.13
Requires-Dist: attrs (>=25.3.0,<26.0.0)
Requires-Dist: fire (>=0.7.0,<0.8.0)
Requires-Dist: pyyaml (>=6.0.2,<7.0.0)
Requires-Dist: requests (>=2.32.3,<3.0.0)
